django_cleanup/__init__.py
django_cleanup/apps.py
django_cleanup/cache.py
django_cleanup/cleanup.py
django_cleanup/handlers.py
django_cleanup/signals.py
django_cleanup-6.0.0.dist-info/LICENSE
django_cleanup-6.0.0.dist-info/METADATA
django_cleanup-6.0.0.dist-info/WHEEL
django_cleanup-6.0.0.dist-info/top_level.txt
django_cleanup-6.0.0.dist-info/RECORD
